{
  "entries": {
    "brew": {
      "git-extras": {
        "version": "6.1.0",
        "bottle": {
          "rebuild": 0,
          "cellar": ":any_skip_relocation",
          "prefix": "/usr/local",
          "root_url": "https://homebrew.bintray.com/bottles",
          "files": {
            "arm64_big_sur": {
              "url": "https://homebrew.bintray.com/bottles/git-extras-6.1.0.arm64_big_sur.bottle.tar.gz",
              "sha256": "a26aa6b1ef178b8c5c8a7fb61ec04e5e0b43fdfe9c253703273c2c3536935826"
            },
            "big_sur": {
              "url": "https://homebrew.bintray.com/bottles/git-extras-6.1.0.big_sur.bottle.tar.gz",
              "sha256": "1ed4aa34fdbb50977413ff1860227d7c66cc339f614ee65fe4b9bbdc82bc224e"
            },
            "catalina": {
              "url": "https://homebrew.bintray.com/bottles/git-extras-6.1.0.catalina.bottle.tar.gz",
              "sha256": "abb85334f41bfa73f650bc138caecf8a35cc0af8951628c97b09d68c30fbbe60"
            },
            "mojave": {
              "url": "https://homebrew.bintray.com/bottles/git-extras-6.1.0.mojave.bottle.tar.gz",
              "sha256": "afe41a9918fd0951a2e2b4badfbb6bca57ca2161d6ef82f452604e1f73154825"
            },
            "high_sierra": {
              "url": "https://homebrew.bintray.com/bottles/git-extras-6.1.0.high_sierra.bottle.tar.gz",
              "sha256": "ffc36aced07c7ca6a5e8ccb8b4dbfcdd50742efd780d9a1b668189813a3486cf"
            }
          }
        }
      },
      "ghq": {
        "version": "1.1.5",
        "bottle": {
          "rebuild": 0,
          "cellar": ":any_skip_relocation",
          "prefix": "/usr/local",
          "root_url": "https://homebrew.bintray.com/bottles",
          "files": {
            "arm64_big_sur": {
              "url": "https://homebrew.bintray.com/bottles/ghq-1.1.5.arm64_big_sur.bottle.tar.gz",
              "sha256": "4b20b63da37b5c05ef8b0da54015a6f16fa08d43ed32920cd980b8243be22967"
            },
            "big_sur": {
              "url": "https://homebrew.bintray.com/bottles/ghq-1.1.5.big_sur.bottle.tar.gz",
              "sha256": "65c3fa300e2dc1f8e20634feb2acb60b7ba2ee9aa17a87dab39acafd4869246d"
            },
            "catalina": {
              "url": "https://homebrew.bintray.com/bottles/ghq-1.1.5.catalina.bottle.tar.gz",
              "sha256": "247f4e7b0964b0a27321b24ae06349d9eac65280345dda17680fa8049c29ac75"
            },
            "mojave": {
              "url": "https://homebrew.bintray.com/bottles/ghq-1.1.5.mojave.bottle.tar.gz",
              "sha256": "a863be3a3b307c82821d0dbed2d4d1faa05aaea9c6dd150d7b3f2a878e4bd79c"
            },
            "high_sierra": {
              "url": "https://homebrew.bintray.com/bottles/ghq-1.1.5.high_sierra.bottle.tar.gz",
              "sha256": "060f3bc0d7b55e04274383faa21b45e8d8457ca61e25fd3416b2fe0d3177036b"
            }
          }
        }
      },
      "tig": {
        "version": "2.5.2",
        "bottle": {
          "rebuild": 0,
          "cellar": ":any_skip_relocation",
          "prefix": "/usr/local",
          "root_url": "https://homebrew.bintray.com/bottles",
          "files": {
            "arm64_big_sur": {
              "url": "https://homebrew.bintray.com/bottles/tig-2.5.2.arm64_big_sur.bottle.tar.gz",
              "sha256": "7c1b4b40c1f893351de1bc4d8c5554eb4c5bae20cd7ac5655ca7bb88e9ae6794"
            },
            "big_sur": {
              "url": "https://homebrew.bintray.com/bottles/tig-2.5.2.big_sur.bottle.tar.gz",
              "sha256": "7182cb61a5f767710e6ad1d62abdd95454396e1dabcf77c6a1eb2fb87352b66a"
            },
            "catalina": {
              "url": "https://homebrew.bintray.com/bottles/tig-2.5.2.catalina.bottle.tar.gz",
              "sha256": "0f63ed7e08ee5099695a7868057ce70903f411bedbf95939bd1161c24b42ccef"
            },
            "mojave": {
              "url": "https://homebrew.bintray.com/bottles/tig-2.5.2.mojave.bottle.tar.gz",
              "sha256": "64c2c022ceb003be21ca97d84a288cd5796c571972735331029af6dab110c57f"
            }
          }
        }
      },
      "robotsandpencils/made/xcodes": {
        "version": "0.16.0",
        "bottle": {
          "rebuild": 0,
          "cellar": ":any_skip_relocation",
          "prefix": "/usr/local",
          "root_url": "https://github.com/RobotsAndPencils/xcodes/releases/download/0.16.0",
          "files": {
            "mojave": {
              "url": "https://github.com/RobotsAndPencils/xcodes/releases/download/0.16.0/xcodes-0.16.0.mojave.bottle.tar.gz",
              "sha256": "c4f625edb2f3aa8b5669e8cf5ba75430585e0d76f7632a37f921a2ecfaf8d2ff"
            }
          }
        }
      },
      "xcodes": {
        "version": "0.16.0",
        "bottle": {
          "rebuild": 0,
          "cellar": ":any_skip_relocation",
          "prefix": "/usr/local",
          "root_url": "https://github.com/RobotsAndPencils/xcodes/releases/download/0.16.0",
          "files": {
            "mojave": {
              "url": "https://github.com/RobotsAndPencils/xcodes/releases/download/0.16.0/xcodes-0.16.0.mojave.bottle.tar.gz",
              "sha256": "c4f625edb2f3aa8b5669e8cf5ba75430585e0d76f7632a37f921a2ecfaf8d2ff"
            }
          }
        }
      },
      "maven": {
        "version": "3.6.3_1",
        "bottle": false
      },
      "z": {
        "version": "1.9",
        "bottle": false
      }
    },
    "tap": {
      "robotsandpencils/made": {
        "revision": "f94247479cec56e17138abdd942ff669b0c76843"
      },
      "adoptopenjdk/openjdk": {
        "revision": "acb102fa1a03a7d3e24b363bd864e6cc1f4b7f0f"
      }
    },
    "cask": {
      "spotify": {
        "version": "1.1.52.687.gf5565fe5,1.1.52.687.gf5565fe5-30",
        "options": {
          "full_name": "spotify"
        }
      },
      "slack": {
        "version": "4.12.2",
        "options": {
          "full_name": "slack"
        }
      },
      "adoptopenjdk11": {
        "version": "11.0.10,9",
        "options": {
          "full_name": "adoptopenjdk11"
        }
      }
    }
  },
  "system": {
    "macos": {
      "catalina": {
        "HOMEBREW_VERSION": "3.0.1",
        "HOMEBREW_PREFIX": "/usr/local",
        "Homebrew/homebrew-core": "a9a90b59a70072aa62b1189a124196efcbe10f9f",
        "CLT": "12.4.0.0.1.1610135815",
        "Xcode": "12.4",
        "macOS": "10.15.7"
      },
      "big_sur": {
        "HOMEBREW_VERSION": "3.0.1",
        "HOMEBREW_PREFIX": "/usr/local",
        "Homebrew/homebrew-core": "a9a90b59a70072aa62b1189a124196efcbe10f9f",
        "CLT": "12.4.0.0.1.1610135815",
        "Xcode": "12.4",
        "macOS": "11.2.1"
      }
    }
  }
}
